Workbook

Sheet Read Me
A2: Record sequence
B3: FHEAD - once, first line
B4: THEAD - one per document
B5: TDETL - merchandise item lines (0...n)
B6: TALLW - allowances, must follow their TDETL (0...n) -- not required now
B7: TNMRC - non-merchandise costs (0...n)
B8: TVATS - tax breakdown by tax code (0...n)
B9: TTAIL - closes the document
B10: FTAIL - once, last line
A12: Formatting rules
B13: Character fields: left justified, right padded with blanks.
B14: Numeric fields: right justified, left padded with zeroes.
B15: Decimals are implied - no decimal point is written. Number(20,4) means 20 characters of which the last 4 are decimals; Number(20,10) means the last 10 are decimals.
B16: Amounts carry an explicit sign field (+ / -) immediately in front of them; the value itself is unsigned.
B17: Dates are Char(14) in YYYYMMDDHH24MISS format.
B18: Null values are blank (spaces).
B19: Every record is padded to its full fixed length - the program rejects a record whose length does not match.

Sheet Record Summary
A1: Record types in the ediinvcupld input file
A3: Record | B3: Descriptor value | C3: Purpose | D3: Occurrence | E3: Record length (chars) | F3: Number of fields | G3: Detail sheet
A4: FHEAD | B4: FHEAD | C4: File header | D4: 1 (first line) | E4: =FHEAD!E9 -> 34 | F4: 4 | G4: see sheet FHEAD
A5: THEAD | B5: THEAD | C5: Transaction (document) header | D5: 1...n | E5: =THEAD!E43 -> 631 | F5: 37 | G5: see sheet THEAD
A6: TDETL | B6: TDETL | C6: Merchandise item detail | D6: 0...n per THEAD | E6: =TDETL!E20 -> 191 | F6: 15 | G6: see sheet TDETL
A7: TALLW | B7: TALLW | C7: Allowance for the preceding TDETL item | D7: 0...n per TDETL | E7: ='TALLW(Not required)'!E13 -> 78 | F7: 8 | G7: see sheet TALLW (Not required)
A8: TNMRC | B8: TNMRC | C8: Non-merchandise cost | D8: 0...n per THEAD | E8: =TNMRC!E15 -> 89 | F8: 10 | G8: see sheet TNMRC
A9: TVATS | B9: TVATS | C9: VAT/tax breakdown by tax code | D9: 0...n per THEAD | E9: =TVATS!E12 -> 72 | F9: 7 | G9: see sheet TVATS
A10: TTAIL | B10: TTAIL | C10: Transaction trailer | D10: 1 per THEAD | E10: =TTAIL!E10 -> 31 | F10: 4 | G10: see sheet TTAIL
A11: FTAIL | B11: FTAIL | C11: File trailer | D11: 1 (last line) | E11: =FTAIL!E8 -> 25 | F11: 3 | G11: see sheet FTAIL

Sheet FHEAD
A1: FHEAD - File header
A3: Seq | B3: Field Name | C3: Start | D3: End | E3: Length | F3: Oracle Type | G3: Req | H3: Valid Values / Format | I3: Description & Validation | J3: ReIM Target Column
A4: 1 | B4: Record Descriptor | C4: 1 | D4: =C4+E4-1 -> 5 | E4: 5 | F4: Char(5) | G4: Y | H4: FHEAD | I4: Identifies the record type. Program halts if not FHEAD.
A5: 2 | B5: Line ID | C5: =D4+1 -> 6 | D5: =C5+E5-1 -> 15 | E5: 10 | F5: Number(10) | G5: Y | H5: 0000000001 | I5: Sequential file line number. Must be 0000000001 on FHEAD; halt otherwise.
A6: 3 | B6: Gentran ID | C6: =D5+1 -> 16 | D6: =C6+E6-1 -> 20 | E6: 5 | F6: Char(5) | G6: Y | H6: UPINV | I6: Transaction type of the file. Halt if not UPINV (EDIConstants.UPLOAD_GENTRAN_ID).
A7: 4 | B7: File Date | C7: =D6+1 -> 21 | D7: =C7+E7-1 -> 34 | E7: 14 | F7: Char(14) | G7: Y | H7: YYYYMMDDHH24MISS | I7: Date/time the file was created. Halt if not a valid date.
B9: Total record length | E9: =SUM(E4:E7) -> 34

Sheet THEAD
A1: THEAD - Transaction (document) header
A2: Fixed-width record, 631 characters (EDIConstants.LEN_REC_THEAD = 631). Occurrence: 1...n. Source: com.retek.reim.batch.ediupinv (ReIM 13.1.6 reim13.war), cross-checked against the ReIM Operations Guide.
A4: Seq | B4: Field Name | C4: Start | D4: End | E4: Length | F4: Oracle Type | G4: Req | H4: Valid Values / Format | I4: Description & Validation | J4: ReIM Target Column
A5: 1 | B5: Record Descriptor | C5: 1 | D5: =C5+E5-1 -> 5 | E5: 5 | F5: Char(5) | G5: Y | H5: THEAD | I5: Identifies the record type. Halt if out of sequence.
A6: 2 | B6: Line ID | C6: =D5+1 -> 6 | D6: =C6+E6-1 -> 15 | E6: 10 | F6: Number(10) | G6: Y | H6: sequential | I6: Sequential file line number; must continue the file sequence.
A7: 3 | B7: Transaction Number | C7: =D6+1 -> 16 | D7: =C7+E7-1 -> 25 | E7: 10 | F7: Number(10) | G7: Y | H7: sequential | I7: Document/transaction number. First THEAD must be 0000000001; all child records repeat it.
A8: 4 | B8: Document Type | C8: =D7+1 -> 26 | D8: =C8+E8-1 -> 31 | E8: 6 | F8: Char(6) | G8: Y | H8: MRCHI, NMRCHI, CRDNT, DEBMEC, DEBMEQ, CRDNRC, CRDNRQ | I8: Type of document. Reject transaction if null or not in the accepted set. | J8: IM_DOC_HEAD.DOC_TYPE
A9: 5 | B9: Vendor Document Number | C9: =D8+1 -> 32 | D9: =C9+E9-1 -> 61 | E9: 30 | F9: Char(30) | G9: Y | H9: free text | I9: Supplier's own document number; up-shifted by the program. Must be unique for the vendor. | J9: IM_DOC_HEAD.EXT_DOC_ID
A10: 6 | B10: Group ID | C10: =D9+1 -> 62 | D10: =C10+E10-1 -> 71 | E10: 10 | F10: Char(10) | G10: N | H10: numeric | I10: Informational grouping value for invoices. Present in this 13.1.6 build; not in the base 13.x OG layout. | J10: IM_DOC_HEAD.GROUP_ID
A11: 7 | B11: Vendor Type | C11: =D10+1 -> 72 | D11: =C11+E11-1 -> 77 | E11: 6 | F11: Char(6) | G11: Y | H11: SUPP, BK, AG, FF, IM, BR, FA, AP, CO, CN, S1, S2, S3 | I11: Partner/vendor type. Reject transaction if null or invalid. | J11: IM_DOC_HEAD.VENDOR_TYPE
A12: 8 | B12: Vendor ID | C12: =D11+1 -> 78 | D12: =C12+E12-1 -> 87 | E12: 10 | F12: Char(10) | G12: Y | H12: numeric | I12: Supplier site / partner ID. Must be numeric and exist; reject transaction otherwise. | J12: IM_DOC_HEAD.VENDOR_ID
A13: 9 | B13: Vendor Document Date | C13: =D12+1 -> 88 | D13: =C13+E13-1 -> 101 | E13: 14 | F13: Char(14) | G13: Y | H13: YYYYMMDDHH24MISS | I13: Date the supplier issued the document. | J13: IM_DOC_HEAD.DOC_DATE
A14: 10 | B14: Order Number / RTV Order Number | C14: =D13+1 -> 102 | D14: =C14+E14-1 -> 111 | E14: 10 | F14: Number(10) | G14: N | H14: numeric | I14: Merchandising (RMS) order number, or the RTV order number when RTV Ind = Y. | J14: IM_DOC_HEAD.ORDER_NO
A15: 11 | B15: Location | C15: =D14+1 -> 112 | D15: =C15+E15-1 -> 121 | E15: 10 | F15: Number(10) | G15: Y | H15: numeric | I15: Merchandising location the document is for. Must exist in RMS. | J15: IM_DOC_HEAD.LOCATION
A16: 12 | B16: Location Type | C16: =D15+1 -> 122 | D16: =C16+E16-1 -> 122 | E16: 1 | F16: Char(1) | G16: N | H16: S = store, W = warehouse | I16: Location type; rejected if populated while Location is null. | J16: IM_DOC_HEAD.LOC_TYPE
A17: 13 | B17: Terms | C17: =D16+1 -> 123 | D17: =C17+E17-1 -> 137 | E17: 15 | F17: Char(15) | G17: N | H17: valid terms code | I17: Payment terms. Defaults to the supplier's terms when blank. | J17: IM_DOC_HEAD.TERMS
A18: 14 | B18: Due Date | C18: =D17+1 -> 138 | D18: =C18+E18-1 -> 151 | E18: 14 | F18: Char(14) | G18: N | H18: YYYYMMDDHH24MISS | I18: Payment due date. Calculated from terms when blank; must not precede the document date. | J18: IM_DOC_HEAD.DUE_DATE
A19: 15 | B19: Payment Method | C19: =D18+1 -> 152 | D19: =C19+E19-1 -> 157 | E19: 6 | F19: Char(6) | G19: N | H19: valid payment method | I19: Method used to pay the document. | J19: IM_DOC_HEAD.PAYMENT_METHOD
... A21: 17 | B21: Exchange Rate | C21: =D20+1 -> 161 | D21: =C21+E21-1 -> 172 | E21: 12 | F21: Number(12,4) | G21: N | H21: numeric, implied decimals | I21: Rate to the primary currency. Derived from RMS when blank. | J21: IM_DOC_HEAD.EXCHANGE_RATE
A22: 18 | B22: Sign Indicator - Total Cost | C22: =D21+1 -> 173 | D22: =C22+E22-1 -> 173 | E22: 1 | F22: Char(1) | G22: Y | H22: + or - | I22: Sign of the Total Cost that follows.
A23: 19 | B23: Total Cost | C23: =D22+1 -> 174 | D23: =C23+E23-1 -> 193 | E23: 20 | F23: Number(20,4) | G23: N | H23: numeric, implied decimals | I23: Total document cost in document currency; must reconcile to the TDETL/TNMRC lines. | J23: IM_DOC_HEAD.TOTAL_COST / RESOLUTION_ADJUSTED_TOTAL_COST
A24: 20 | B24: Sign Indicator - Total VAT | C24: =D23+1 -> 194 | D24: =C24+E24-1 -> 194 | E24: 1 | F24: Char(1) | G24: Y | H24: + or - | I24: Sign of the Total VAT Amount that follows.
A25: 21 | B25: Total VAT Amount | C25: =D24+1 -> 195 | D25: =C25+E25-1 -> 214 | E25: 20 | F25: Number(20,4) | G25: N | H25: numeric, implied decimals | I25: Total tax on the document; treated as zero when blank. Must reconcile to TVATS / detail tax. | J25: IM_DOC_HEAD (total VAT amount)
A26: 22 | B26: Sign Indicator - Total Quantity | C26: =D25+1 -> 215 | D26: =C26+E26-1 -> 215 | E26: 1 | F26: Char(1) | G26: Y | H26: + or - | I26: Sign of the Total Quantity that follows.
A27: 23 | B27: Total Quantity | C27: =D26+1 -> 216 | D27: =C27+E27-1 -> 227 | E27: 12 | F27: Number(12,4) | G27: Y | H27: numeric, implied decimals | I27: Total quantity in EACHES; must equal the sum of TDETL quantities. Must be zero for NMRCHI. | J27: IM_DOC_HEAD.TOTAL_QTY / RESOLUTION_ADJUSTED_TOTAL_QTY
A28: 24 | B28: Sign Indicator - Total Discount | C28: =D27+1 -> 228 | D28: =C28+E28-1 -> 228 | E28: 1 | F28: Char(1) | G28: Y | H28: + or - | I28: Sign of the Total Discount that follows.
A29: 25 | B29: Total Discount | C29: =D28+1 -> 229 | D29: =C29+E29-1 -> 240 | E29: 12 | F29: Number(12,4) | G29: Y | H29: numeric, implied decimals | I29: Total discount applied to the document. | J29: IM_DOC_HEAD.TOTAL_DISCOUNT
A30: 26 | B30: Freight Type | C30: =D29+1 -> 241 | D30: =C30+E30-1 -> 246 | E30: 6 | F30: Char(6) | G30: N | H30: valid freight type | I30: Freight terms for the document. | J30: IM_DOC_HEAD.FREIGHT_TYPE
A31: 27 | B31: Paid Indicator | C31: =D30+1 -> 247 | D31: =C31+E31-1 -> 247 | E31: 1 | F31: Char(1) | G31: Y | H31: Y or N | I31: Document already paid outside ReIM. | J31: IM_DOC_HEAD.MANUALLY_PAID_IND
A32: 28 | B32: Multi Location Indicator | C32: =D31+1 -> 248 | D32: =C32+E32-1 -> 248 | E32: 1 | F32: Char(1) | G32: Y | H32: Y or N | I32: Y routes the document to the parent-invoice tables instead of a single-location invoice. | J32: IM_PARENT_INVOICE (when Y)
A33: 29 | B33: Consignment / Merchandise Type | C33: =D32+1 -> 249 | D33: =C33+E33-1 -> 249 | E33: 1 | F33: Char(1) | G33: Y | H33: C, D or E (EDI_MERCH_TYPES) | I33: Java field merchType. The 13.x OG labels this position the consignment indicator; this build validates it against C/D/E - confirm the code your supplier sends. | J33: IM_DOC_HEAD (merch type / consignment)
A34: 30 | B34: Deal ID | C34: =D33+1 -> 250 | D34: =C34+E34-1 -> 259 | E34: 10 | F34: Number(10) | G34: N | H34: numeric | I34: RMS deal ID for deal bill-back documents. Requires a Deal Approval Indicator of M or A. | J34: IM_DOC_HEAD.DEAL_ID
A35: 31 | B35: Deal Approval Indicator | C35: =D34+1 -> 260 | D35: =C35+E35-1 -> 260 | E35: 1 | F35: Char(1) | G35: N | H35: M = submitted, A = approved | I35: Approval status of the deal named above.
A36: 32 | B36: RTV Indicator | C36: =D35+1 -> 261 | D36: =C36+E36-1 -> 261 | E36: 1 | F36: Char(1) | G36: Y | H36: Y or N | I36: Marks the document as a return-to-vendor document. | J36: IM_DOC_HEAD.RTV_IND
A37: 33 | B37: Custom Document Reference 1 | C37: =D36+1 -> 262 | D37: =C37+E37-1 -> 351 | E37: 90 | F37: Char(90) | G37: N | H37: free text | I37: Client customisation field; no validation. NOTE: 90 in this build, the base 13.x OG prints 30. | J37: IM_DOC_HEAD.CUSTOM_REF_1
A38: 34 | B38: Custom Document Reference 2 | C38: =D37+1 -> 352 | D38: =C38+E38-1 -> 441 | E38: 90 | F38: Char(90) | G38: N | H38: free text | I38: Client customisation field; no validation. | J38: IM_DOC_HEAD.CUSTOM_REF_2
A39: 35 | B39: Custom Document Reference 3 | C39: =D38+1 -> 442 | D39: =C39+E39-1 -> 531 | E39: 90 | F39: Char(90) | G39: N | H39: free text | I39: Client customisation field; no validation. | J39: IM_DOC_HEAD.CUSTOM_REF_3
A40: 36 | B40: Custom Document Reference 4 | C40: =D39+1 -> 532 | D40: =C40+E40-1 -> 621 | E40: 90 | F40: Char(90) | G40: N | H40: free text | I40: Client customisation field; no validation. | J40: IM_DOC_HEAD.CUSTOM_REF_4
A41: 37 | B41: Cross-Reference Document Number | C41: =D40+1 -> 622 | D41: =C41+E41-1 -> 631 | E41: 10 | F41: Number(10) | G41: N | H41: numeric | I41: ReIM document the credit note/debit memo refers to. Blank for non-merchandise invoices. | J41: IM_DOC_HEAD.REF_DOC
B43: Total record length | E43: =SUM(E5:E41) -> 631

Sheet TDETL
A1: TDETL - Merchandise item detail
A3: Seq | B3: Field Name | C3: Start | D3: End | E3: Length | F3: Oracle Type | G3: Req | H3: Valid Values / Format | I3: Description & Validation | J3: ReIM Target Column
A4: 1 | B4: Record Descriptor | C4: 1 | D4: =C4+E4-1 -> 5 | E4: 5 | F4: Char(5) | G4: Y | H4: TDETL | I4: Identifies the record type.
A5: 2 | B5: Line ID | C5: =D4+1 -> 6 | D5: =C5+E5-1 -> 15 | E5: 10 | F5: Number(10) | G5: Y | H5: sequential | I5: Sequential file line number.
A6: 3 | B6: Transaction Number | C6: =D5+1 -> 16 | D6: =C6+E6-1 -> 25 | E6: 10 | F6: Number(10) | G6: Y | H6: matches THEAD | I6: Must equal the transaction number of the open THEAD.
A7: 4 | B7: UPC | C7: =D6+1 -> 26 | D7: =C7+E7-1 -> 50 | E7: 25 | F7: Char(25) | G7: Y* | H7: UPC / EAN | I7: Item identified by UPC. Exactly one of UPC, Item or VPN must be populated. | J7: IM_INVOICE_DETAIL.ITEM
A8: 5 | B8: UPC Supplement | C8: =D7+1 -> 51 | D8: =C8+E8-1 -> 55 | E8: 5 | F8: Number(5) | G8: N | H8: numeric | I8: UPC supplement; legacy field, normally blank.
A9: 6 | B9: Item | C9: =D8+1 -> 56 | D9: =C9+E9-1 -> 80 | E9: 25 | F9: Char(25) | G9: Y* | H9: RMS item number | I9: Item identified by RMS item number. Exactly one of UPC, Item or VPN. | J9: IM_INVOICE_DETAIL.ITEM
A10: 7 | B10: VPN | C10: =D9+1 -> 81 | D10: =C10+E10-1 -> 110 | E10: 30 | F10: Char(30) | G10: Y* | H10: vendor product number | I10: Item identified by the supplier's product number. Exactly one of UPC, Item or VPN. | J10: IM_INVOICE_DETAIL.ITEM (resolved)
A11: 8 | B11: Sign Indicator - Quantity | C11: =D10+1 -> 111 | D11: =C11+E11-1 -> 111 | E11: 1 | F11: Char(1) | G11: Y | H11: + or - | I11: Sign of the quantity that follows.
A12: 9 | B12: Original Document Quantity | C12: =D11+1 -> 112 | D12: =C12+E12-1 -> 123 | E12: 12 | F12: Number(12,4) | G12: Y | H12: numeric, implied decimals | I12: Invoiced quantity in EACHES. | J12: IM_INVOICE_DETAIL.INVOICE_QTY / RESOLUTION_ADJUSTED_QTY
A13: 10 | B13: Sign Indicator - Unit Cost | C13: =D12+1 -> 124 | D13: =C13+E13-1 -> 124 | E13: 1 | F13: Char(1) | G13: Y | H13: + or - | I13: Sign of the unit cost that follows.
A14: 11 | B14: Original Unit Cost | C14: =D13+1 -> 125 | D14: =C14+E14-1 -> 144 | E14: 20 | F14: Number(20,4) | G14: Y | H14: numeric, implied decimals | I14: Unit cost in document currency. | J14: IM_INVOICE_DETAIL.UNIT_COST / RESOLUTION_ADJUSTED_UNIT_COST
A15: 12 | B15: Original VAT Code | C15: =D14+1 -> 145 | D15: =C15+E15-1 -> 150 | E15: 6 | F15: Char(6) | G15: Y | H15: valid VAT code | I15: Tax code applied to this item. | J15: IM_INVOICE_DETAIL (tax code)
A16: 13 | B16: Original VAT Rate | C16: =D15+1 -> 151 | D16: =C16+E16-1 -> 170 | E16: 20 | F16: Number(20,10) | G16: Y | H16: numeric, implied decimals | I16: Tax rate for the code above. | J16: IM_INVOICE_DETAIL (tax rate)
A17: 14 | B17: Sign Indicator - Total Allowance | C17: =D16+1 -> 171 | D17: =C17+E17-1 -> 171 | E17: 1 | F17: Char(1) | G17: Y | H17: + or - | I17: Sign of the total allowance that follows.
A18: 15 | B18: Total Allowance | C18: =D17+1 -> 172 | D18: =C18+E18-1 -> 191 | E18: 20 | F18: Number(20,4) | G18: Y | H18: numeric, implied decimals | I18: Sum of the TALLW records for this item; 0 when there are none. Must be 0 for CRDNT. | J18: IM_INVOICE_DETAIL (allowance total)
B20: Total record length | E20: =SUM(E4:E18) -> 191

Sheet TALLW(Not required)
A1: TALLW - Allowance for the preceding TDETL item | F1: (Not required)
A3: Seq | B3: Field Name | C3: Start | D3: End | E3: Length | F3: Oracle Type | G3: Req | H3: Valid Values / Format | I3: Description & Validation | J3: ReIM Target Column
A4: 1 | B4: Record Descriptor | C4: 1 | D4: =C4+E4-1 -> 5 | E4: 5 | F4: Char(5) | G4: Y | H4: TALLW | I4: Identifies the record type. Must follow its TDETL record.
A5: 2 | B5: Line ID | C5: =D4+1 -> 6 | D5: =C5+E5-1 -> 15 | E5: 10 | F5: Number(10) | G5: Y | H5: sequential | I5: Sequential file line number.
A6: 3 | B6: Transaction Number | C6: =D5+1 -> 16 | D6: =C6+E6-1 -> 25 | E6: 10 | F6: Number(10) | G6: Y | H6: matches THEAD | I6: Must equal the transaction number of the open THEAD.
A7: 4 | B7: Allowance Code | C7: =D6+1 -> 26 | D7: =C7+E7-1 -> 31 | E7: 6 | F7: Char(6) | G7: Y | H7: valid allowance code | I7: Type of allowance. Rejected if null or not set up in ReIM. | J7: IM_INVOICE_DETAIL_ALLOWANCE.ALLOWANCE_CODE
A8: 5 | B8: Sign Indicator - Allowance Amount | C8: =D7+1 -> 32 | D8: =C8+E8-1 -> 32 | E8: 1 | F8: Char(1) | G8: Y | H8: + or - | I8: Sign of the allowance amount that follows.
A9: 6 | B9: Allowance Amount | C9: =D8+1 -> 33 | D9: =C9+E9-1 -> 52 | E9: 20 | F9: Number(20,4) | G9: Y | H9: numeric, implied decimals | I9: Allowance value in document currency. | J9: IM_INVOICE_DETAIL_ALLOWANCE.ALLOWANCE_AMOUNT
A10: 7 | B10: Allowance VAT Code | C10: =D9+1 -> 53 | D10: =C10+E10-1 -> 58 | E10: 6 | F10: Char(6) | G10: Y | H10: valid VAT code | I10: Tax code applied to the allowance.
A11: 8 | B11: Allowance VAT Rate | C11: =D10+1 -> 59 | D11: =C11+E11-1 -> 78 | E11: 20 | F11: Number(20,10) | G11: Y | H11: numeric, implied decimals | I11: Tax rate for the code above.
B13: Total record length | E13: =SUM(E4:E11) -> 78

Sheet TNMRC
A1: TNMRC - Non-merchandise cost
A3: Seq | B3: Field Name | C3: Start | D3: End | E3: Length | F3: Oracle Type | G3: Req | H3: Valid Values / Format | I3: Description & Validation | J3: ReIM Target Column
A4: 1 | B4: Record Descriptor | C4: 1 | D4: =C4+E4-1 -> 5 | E4: 5 | F4: Char(5) | G4: Y | H4: TNMRC | I4: Identifies the record type.
A5: 2 | B5: Line ID | C5: =D4+1 -> 6 | D5: =C5+E5-1 -> 15 | E5: 10 | F5: Number(10) | G5: Y | H5: sequential | I5: Sequential file line number.
A6: 3 | B6: Transaction Number | C6: =D5+1 -> 16 | D6: =C6+E6-1 -> 25 | E6: 10 | F6: Number(10) | G6: Y | H6: matches THEAD | I6: Must equal the transaction number of the open THEAD.
A7: 4 | B7: Non-Merchandise Code | C7: =D6+1 -> 26 | D7: =C7+E7-1 -> 31 | E7: 6 | F7: Char(6) | G7: Y | H7: valid non-merch code | I7: Type of non-merchandise cost. Rejected if null or invalid. | J7: IM_DOC_NON_MERCH.NON_MERCH_CODE
A8: 5 | B8: Sign Indicator - Amount | C8: =D7+1 -> 32 | D8: =C8+E8-1 -> 32 | E8: 1 | F8: Char(1) | G8: Y | H8: + or - | I8: Sign of the non-merchandise amount that follows.
A9: 6 | B9: Non-Merchandise Amount | C9: =D8+1 -> 33 | D9: =C9+E9-1 -> 52 | E9: 20 | F9: Number(20,4) | G9: Y | H9: numeric, implied decimals | I9: Cost in document currency. Must be negative when the document type is CRDNT. | J9: IM_DOC_NON_MERCH.NON_MERCH_AMT
A10: 7 | B10: Non-Merchandise VAT Code | C10: =D9+1 -> 53 | D10: =C10+E10-1 -> 58 | E10: 6 | F10: Char(6) | G10: Y | H10: valid VAT code | I10: Tax code applied to the non-merchandise cost.
A11: 8 | B11: Non-Merchandise VAT Rate | C11: =D10+1 -> 59 | D11: =C11+E11-1 -> 78 | E11: 20 | F11: Number(20,10) | G11: Y | H11: numeric, implied decimals | I11: Tax rate for the code above.
A12: 9 | B12: Service Performed Indicator | C12: =D11+1 -> 79 | D12: =C12+E12-1 -> 79 | E12: 1 | F12: Char(1) | G12: Y | H12: Y or N | I12: Whether the service has been performed. Rejected if null or not Y/N. | J12: IM_DOC_NON_MERCH.SERVICE_PERF_IND
A13: 10 | B13: Store | C13: =D12+1 -> 80 | D13: =C13+E13-1 -> 89 | E13: 10 | F13: Number(10) | G13: N | H13: numeric | I13: Store where the service was performed; validated when the indicator is Y. | J13: IM_DOC_NON_MERCH.STORE
B15: Total record length | E15: =SUM(E4:E13) -> 89

Sheet TVATS
A1: TVATS - VAT/tax breakdown by tax code
A3: Seq | B3: Field Name | C3: Start | D3: End | E3: Length | F3: Oracle Type | G3: Req | H3: Valid Values / Format | I3: Description & Validation | J3: ReIM Target Column
A4: 1 | B4: Record Descriptor | C4: 1 | D4: =C4+E4-1 -> 5 | E4: 5 | F4: Char(5) | G4: Y | H4: TVATS | I4: Identifies the record type. (EDIConstants names the field TTAXS but its value is TVATS.)
A5: 2 | B5: Line ID | C5: =D4+1 -> 6 | D5: =C5+E5-1 -> 15 | E5: 10 | F5: Number(10) | G5: Y | H5: sequential | I5: Sequential file line number.
A6: 3 | B6: Transaction Number | C6: =D5+1 -> 16 | D6: =C6+E6-1 -> 25 | E6: 10 | F6: Number(10) | G6: Y | H6: matches THEAD | I6: Must equal the transaction number of the open THEAD.
A7: 4 | B7: VAT Code | C7: =D6+1 -> 26 | D7: =C7+E7-1 -> 31 | E7: 6 | F7: Char(6) | G7: Y | H7: valid VAT code | I7: Tax code the cost below is taxed at. | J7: IM_DOC_TAX (tax code)
A8: 5 | B8: VAT Rate | C8: =D7+1 -> 32 | D8: =C8+E8-1 -> 51 | E8: 20 | F8: Number(20,10) | G8: Y | H8: numeric, implied decimals | I8: Tax rate for the code above. | J8: IM_DOC_TAX (tax rate)
A9: 6 | B9: Sign Indicator - Cost | C9: =D8+1 -> 52 | D9: =C9+E9-1 -> 52 | E9: 1 | F9: Char(1) | G9: Y | H9: + or - | I9: Sign of the taxable cost that follows.
A10: 7 | B10: Cost at this VAT Code | C10: =D9+1 -> 53 | D10: =C10+E10-1 -> 72 | E10: 20 | F10: Number(20,4) | G10: Y | H10: numeric, implied decimals | I10: Total document amount taxed at this rate (tax basis). | J10: IM_DOC_TAX (tax basis)
B12: Total record length | E12: =SUM(E4:E10) -> 72

Sheet TTAIL
A1: TTAIL - Transaction trailer
A2: Fixed-width record, 31 characters (EDIConstants.LEN_REC_TTAIL = 31). Occurrence: 1 per THEAD. Source: com.retek.reim.batch.ediupinv (ReIM 13.1.6 reim13.war), cross-checked against the ReIM Operations Guide.
A4: Seq | B4: Field Name | C4: Start | D4: End | E4: Length | F4: Oracle Type | G4: Req | H4: Valid Values / Format | I4: Description & Validation | J4: ReIM Target Column
A5: 1 | B5: Record Descriptor | C5: 1 | D5: =C5+E5-1 -> 5 | E5: 5 | F5: Char(5) | G5: Y | H5: TTAIL | I5: Identifies the record type; closes the open transaction.
A6: 2 | B6: Line ID | C6: =D5+1 -> 6 | D6: =C6+E6-1 -> 15 | E6: 10 | F6: Number(10) | G6: Y | H6: sequential | I6: Sequential file line number.
A7: 3 | B7: Transaction Number | C7: =D6+1 -> 16 | D7: =C7+E7-1 -> 25 | E7: 10 | F7: Number(10) | G7: Y | H7: matches THEAD | I7: Transaction being closed.
A8: 4 | B8: Transaction Lines | C8: =D7+1 -> 26 | D8: =C8+E8-1 -> 31 | E8: 6 | F8: Number(6) | G8: Y | H8: numeric | I8: Count of detail lines inside the transaction. Must match the actual count and must not be zero.
B10: Total record length | E10: =SUM(E5:E8) -> 31

Sheet FTAIL
A1: FTAIL - File trailer
A3: Seq | B3: Field Name | C3: Start | D3: End | E3: Length | F3: Oracle Type | G3: Req | H3: Valid Values / Format | I3: Description & Validation | J3: ReIM Target Column
A4: 1 | B4: Record Descriptor | C4: 1 | D4: =C4+E4-1 -> 5 | E4: 5 | F4: Char(5) | G4: Y | H4: FTAIL | I4: Identifies the record type. Halt if not FTAIL.
A5: 2 | B5: Line ID | C5: =D4+1 -> 6 | D5: =C5+E5-1 -> 15 | E5: 10 | F5: Number(10) | G5: Y | H5: sequential | I5: Sequential file line number.
A6: 3 | B6: Number of Lines | C6: =D5+1 -> 16 | D6: =C6+E6-1 -> 25 | E6: 10 | F6: Number(10) | G6: Y | H6: numeric | I6: Total lines in the file excluding FHEAD and FTAIL. Halt on mismatch or when the value implies an empty file.
B8: Total record length | E8: =SUM(E4:E6) -> 25
